aiobloom/__init__.py
aiobloom/aiobloom.py
aiobloom-0.0.6.dist-info/LICENSE
aiobloom-0.0.6.dist-info/METADATA
aiobloom-0.0.6.dist-info/WHEEL
aiobloom-0.0.6.dist-info/top_level.txt
aiobloom-0.0.6.dist-info/RECORD
