Metadata-Version: 2.1
Name: aiobloom
Version: 0.0.6
Summary: async api for bloomfilter using redis
Home-page: https://github.com/jiamo/aiobloom
Author: jiamo
Author-email: life.130815@gmail.com
Maintainer: jiamo
Maintainer-email: life.130815@gmail.com
License: MIT
Platform: UNKNOWN
Classifier: License :: OSI Approved :: MIT License
Classifier: Framework :: AsyncIO
Classifier: Intended Audience :: Developers
Classifier: Programming Language :: Python :: 3.7
Requires-Python: >=3.6
Requires-Dist: aioredis
